tlaplus_jupyter/__init__.py
tlaplus_jupyter/__main__.py
tlaplus_jupyter/install.py
tlaplus_jupyter/kernel.py
tlaplus_jupyter/assets/kernel.js
tlaplus_jupyter-0.1.1.dist-info/LICENSE
tlaplus_jupyter-0.1.1.dist-info/METADATA
tlaplus_jupyter-0.1.1.dist-info/WHEEL
tlaplus_jupyter-0.1.1.dist-info/top_level.txt
tlaplus_jupyter-0.1.1.dist-info/RECORD
