Metadata-Version: 2.1
Name: tlaplus-jupyter
Version: 0.1.1
Summary: Jupyter kernel for TLA⁺
Home-page: https://github.com/kelvich/tlaplus_jupyter
Author: Stas Kelvich
Author-email: stas.kelvich@gmail.com
License: BSD
Keywords: jupyter,tla,tlaplus,pluscal
Platform: Platform Independent
Classifier: Topic :: Software Development :: Interpreters
Classifier: Topic :: Software Development :: Quality Assurance
Classifier: Topic :: Scientific/Engineering :: Mathematics
Requires-Python: >=2.6, !=3.0.*, !=3.1.*, !=3.2.*, !=3.3.*, !=3.4.*
Requires-Dist: notebook (>=5)
Requires-Dist: ipykernel (>=4.10)
Requires-Dist: future (>=0.16)
Requires-Dist: psutil (>=4)
